{
  "_fv": 47,
  "_type": "recipe",
  "definition": {
    "recipeType": "Crafting",
    "recipeRetstackSize": 1,
    "group": "",
    "cookingBookCategory": "MISC",
    "xpReward": 0.0,
    "cookingTime": 200,
    "craftingBookCategory": "EQUIPMENT",
    "recipeShapeless": false,
    "recipeSlots": [
      {
        "value": "CUSTOM:FeatherIngot"
      },
      {
        "value": "CUSTOM:FeatherIngot"
      },
      {
        "value": "CUSTOM:FeatherIngot"
      },
      {
        "value": ""
      },
      {
        "value": "Items.STICK"
      },
      {
        "value": ""
      },
      {
        "value": ""
      },
      {
        "value": "Items.STICK"
      },
      {
        "value": ""
      }
    ],
    "recipeReturnStack": {
      "value": "CUSTOM:FeatherPickaxe"
    },
    "name": "feather_pickaxe_recipe",
    "namespace": "mod"
  }
}